enalp_cli/__init__.py
enalp_cli/enalp_cli.py
enalp_cli/sample.txt
enalp_cli-0.1.0.dist-info/entry_points.txt
enalp_cli-0.1.0.dist-info/LICENSE
enalp_cli-0.1.0.dist-info/WHEEL
enalp_cli-0.1.0.dist-info/METADATA
enalp_cli-0.1.0.dist-info/RECORD
